README.md
setup.cfg
setup.py
deepstreampy/__init__.py
deepstreampy/client.py
deepstreampy/event.py
deepstreampy/jsonpath.py
deepstreampy/presence.py
deepstreampy/record.py
deepstreampy/rpc.py
deepstreampy/utils.py
deepstreampy.egg-info/PKG-INFO
deepstreampy.egg-info/SOURCES.txt
deepstreampy.egg-info/dependency_links.txt
deepstreampy.egg-info/requires.txt
deepstreampy.egg-info/top_level.txt
deepstreampy/constants/__init__.py
deepstreampy/constants/actions.py
deepstreampy/constants/connection_state.py
deepstreampy/constants/event.py
deepstreampy/constants/merge_strategies.py
deepstreampy/constants/message.py
deepstreampy/constants/topic.py
deepstreampy/constants/types.py
deepstreampy/message/__init__.py
deepstreampy/message/connection.py
deepstreampy/message/message_builder.py
deepstreampy/message/message_parser.py
tests/__init__.py
tests/test_client.py
tests/test_event.py
tests/test_message.py
tests/test_presence.py
tests/test_rpc.py
tests/util.py