Metadata-Version: 1.1
Name: deepstreampy
Version: 0.1.51
Summary: A deepstream.io client.
Home-page: https://github.com/Allan-Nava/deepstreampy
Author: Yavor Paunov - Allan Nava
Author-email: contact@yavorpaunov.com
License: MIT
Download-URL: https://github.com/Allan-Nava/deepstreampy/archive/v0.1.51.tar.gz
Platform: UNKNOWN
Classifier: Development Status :: 3 - Alpha
Classifier: Intended Audience :: Developers
Classifier: Topic :: Software Development :: Build Tools
Classifier: License :: OSI Approved :: MIT License
Classifier: Programming Language :: Python :: 3
Classifier: Programming Language :: Python :: 3.4
Classifier: Programming Language :: Python :: 3.5
Classifier: Programming Language :: Python :: 3.6
Classifier: Programming Language :: Python :: 3.7
